vlinder/__init__.py
vlinder/appreciate.py
vlinder/case_exporter.py
vlinder/case_importer.py
vlinder/evaluate.py
vlinder/make_report.py
vlinder/optimize.py
vlinder/trbs.py
vlinder/utils.py
vlinder/visualize.py
vlinder/data/README.md
vlinder/data/template.xlsx
vlinder/data/Beerwiser/csv/case_text_elements.csv
vlinder/data/Beerwiser/csv/configurations.csv
vlinder/data/Beerwiser/csv/decision_makers_options.csv
vlinder/data/Beerwiser/csv/dependencies.csv
vlinder/data/Beerwiser/csv/fixed_inputs.csv
vlinder/data/Beerwiser/csv/generic_text_elements.csv
vlinder/data/Beerwiser/csv/key_output_weights.csv
vlinder/data/Beerwiser/csv/key_outputs.csv
vlinder/data/Beerwiser/csv/scenario_weights.csv
vlinder/data/Beerwiser/csv/scenarios.csv
vlinder/data/Beerwiser/csv/theme_weights.csv
vlinder/data/Beerwiser/json/case_text_elements.json
vlinder/data/Beerwiser/json/configurations.json
vlinder/data/Beerwiser/json/decision_makers_options.json
vlinder/data/Beerwiser/json/dependencies.json
vlinder/data/Beerwiser/json/fixed_inputs.json
vlinder/data/Beerwiser/json/generic_text_elements.json
vlinder/data/Beerwiser/json/key_output_weights.json
vlinder/data/Beerwiser/json/key_outputs.json
vlinder/data/Beerwiser/json/scenario_weights.json
vlinder/data/Beerwiser/json/scenarios.json
vlinder/data/Beerwiser/json/theme_weights.json
vlinder/data/Beerwiser/xlsx/Beerwiser.xlsx
vlinder/data/DSM/csv/case_text_elements.csv
vlinder/data/DSM/csv/configurations.csv
vlinder/data/DSM/csv/decision_makers_options.csv
vlinder/data/DSM/csv/dependencies.csv
vlinder/data/DSM/csv/fixed_inputs.csv
vlinder/data/DSM/csv/generic_text_elements.csv
vlinder/data/DSM/csv/key_output_weights.csv
vlinder/data/DSM/csv/key_outputs.csv
vlinder/data/DSM/csv/scenario_weights.csv
vlinder/data/DSM/csv/scenarios.csv
vlinder/data/DSM/csv/theme_weights.csv
vlinder/data/DSM/json/case_text_elements.json
vlinder/data/DSM/json/configurations.json
vlinder/data/DSM/json/decision_makers_options.json
vlinder/data/DSM/json/dependencies.json
vlinder-1.5.0.dist-info/licenses/LICENSE.md
vlinder-1.5.0.dist-info/METADATA
vlinder-1.5.0.dist-info/WHEEL
vlinder-1.5.0.dist-info/top_level.txt
vlinder-1.5.0.dist-info/RECORD
