Metadata-Version: 2.4
Name: vlinder
Version: 1.5.0
Summary: Package for responsible business decision making
Author: Vlinder team
Project-URL: Homepage, https://github.com/responsible-business-decision-making/trbs
Project-URL: Bug Tracker, https://github.com/responsible-business-decision-making/trbs/issues
Classifier: Programming Language :: Python :: 3
Classifier: License :: OSI Approved :: MIT License
Classifier: Operating System :: OS Independent
Requires-Python: >=3.11
License-File: LICENSE.md
Requires-Dist: pandas~=2.3.2
Requires-Dist: numpy~=2.3.2
Requires-Dist: openpyxl~=3.1.5
Requires-Dist: matplotlib~=3.10.5
Requires-Dist: xlsxwriter~=3.2.5
Requires-Dist: dataframe-image~=0.2.7
Requires-Dist: fpdf2~=2.8.4
Requires-Dist: networkx~=3.5
Requires-Dist: pyvis~=0.3.2
Requires-Dist: webdriver-manager~=4.0.2
Requires-Dist: selenium~=4.35.0
Dynamic: license-file
